Workbook

Sheet 1. Assumptions
B1: Optimistic | C1: Base | D1: Pessimistic | E1: Unit | F1: Can cu / Benchmark
A2: 1. PRODUCT & PRICING
A3: ARPU (VND/khach/thang) | B3: 100 | C3: 80 | D3: 50 | E3: Trieu VND | F3: Salesforce Einstein Enterprise VN 50-150M/thang; Base = 60M base fee + 20M overage
A4: Adoption Rate | B4: 0.002 | C4: 0.0015 | D4: 0.0008 | E4: %/thang | F4: B2B SaaS Enterprise VN 0.08-0.2%/thang (long sales cycle, few targets)
A5: TAM (tong khach tiem nang) | B5: 650 | C5: 650 | D5: 650 | E5: cong ty | F5: 650 Enterprise companies VN (xem Phase 0 - 00 Mo hinh Kinh doanh)
A6: Customers Month 0 | B6: 2 | C6: 1 | D6: 1 | E6: khach | F6: Seed stage: 1-2 pilot customers da ky truoc khi mo ban rong
A8: 2. COGS / KHACH / THANG
A9: Model API Cost | B9: 3 | C9: 4 | D9: 5.5 | E9: Trieu VND | F9: GPT-4 + Embeddings: ~500 calls/thang/khach x 8.000 VND/call
A10: - Data Labeling & QA du lieu | B10: 1 | C10: 1.3 | D10: 2 | E10: Trieu VND | F10: Sales training data labeling + feedback loop hang thang
A11: - Model Retraining (~20%/nam) | B11: 0.8 | C11: 1.2 | D11: 2 | E11: Trieu VND | F11: Fine-tuning hang thang; 20%/nam build cost recur per customer cohort
A12: - Human-in-the-loop QA | B12: 0.6 | C12: 1 | D12: 1.5 | E12: Trieu VND | F12: Sales trainer review AI coaching output truoc khi gui khach
A13: - Compliance & Security | B13: 0.4 | C13: 0.5 | D13: 1 | E13: Trieu VND | F13: PDPA audit, SOC 2, data residency VN, encryption
A14: Infrastructure | B14: 1.5 | C14: 2 | D14: 3 | E14: Trieu VND | F14: Multi-region deploy, VectorDB, monitoring, 99.9% SLA, phan bo/khach
A15: Total COGS / khach / thang | B15: =SUM(B9:B14) | C15: =SUM(C9:C14) | D15: =SUM(D9:D14) | E15: M
A17: 3. CUSTOMER BEHAVIOR
A18: Monthly Churn Rate | B18: 0.01 | C18: 0.015 | D18: 0.0225 | E18: %/thang | F18: Enterprise SaaS 1-2%/thang (sticky, long contract). Pess = Base x 1.5
A20: 4. SALES & MARKETING
A21: CAC (Customer Acquisition Cost) | B21: 120 | C21: 150 | D21: 225 | E21: Trieu VND | F21: Enterprise: 2 AE x 6-9 thang sales cycle + sales ops. Pess = Base x 1.5
A23: 5. FIXED COSTS / THANG
A24: Salaries | B24: 250 | C24: 300 | D24: 170 | E24: Trieu VND | F24: Base = Founder 40M + 2 AE 70M + Sales Ops 25M + 2 Eng 90M + PM 30M + CS 25M ~ 280-300M. Pess = crisis mode: chi giu Founder 40M + 1 AE 35M + 1 Eng 45M + PM 30M = 150-170M (cat Sales Ops, 1 AE, 1 Eng, CS - Plan B khi thi truong xau)
A25: Office & Tools | B25: 50 | C25: 70 | D25: 50 | E25: Trieu VND | F25: Van phong + SaaS tool stack. Pess chuyen remote-only de tiet kiem
A26: Marketing Budget (brand/content) | B26: 40 | C26: 60 | D26: 30 | E26: Trieu VND | F26: Content, event, ABM - KHONG trung voi chi phi CAC (muc 4). Pess cat 50% (30M) nhu mot phan Plan B cat giam chi phi khi thi truong xau
A27: Total Fixed Costs / thang | B27: =SUM(B24:B26) | C27: =SUM(C24:C26) | D27: =SUM(D24:D26) | E27: M
A29: 6. INVESTMENT & CASH
A30: Initial Investment (Month 0) | B30: 1200 | C30: 1500 | D30: 1500 | E30: Trieu VND | F30: Engineering 800M + Infra 300M + Marketing 400M (MVP build, 1 lan)
A31: Initial Cash (runway buffer) | B31: 4000 | C31: 5000 | D31: 5000 | E31: Trieu VND | F31: Series Seed VN 2024 (4-7B typical). Pess giu nguyen 5.000M nhu Base: day la so tien da huy dong tai Month 0, khong phu thuoc kich ban tuong lai xay ra
A32: Discount Rate (nam) | B32: 0.15 | C32: 0.25 | D32: 0.4 | E32: %/nam | F32: SaaS seed-stage valuation discount rate; Pess cao hon do rui ro von cao hon
A34: RANG BUOC KIEM TRA (TU DONG)
A35: Hidden Costs / API Cost % | B35: =SUM(B10:B13)/B9 | C35: =SUM(C10:C13)/C9 | D35: =SUM(D10:D13)/D9 | E35: phai >= 30%
A36: Pess Churn / Base Churn | D36: =D18/C18 | E36: phai >= 1.5x
A37: Pess CAC / Base CAC | D37: =D21/C21 | E37: phai >= 1.5x

Sheet 2. Unit Economics
A1: Metric | B1: Optimistic | C1: Base | D1: Pessimistic
A2: ARPU (Trieu VND/khach/thang) | B2: ='1. Assumptions'!B3 | C2: ='1. Assumptions'!C3 | D2: ='1. Assumptions'!D3
A3: Total COGS (Trieu VND/khach/thang) | B3: ='1. Assumptions'!B15 | C3: ='1. Assumptions'!C15 | D3: ='1. Assumptions'!D15
A4: Gross Profit (Trieu VND/khach/thang) | B4: =B2-B3 | C4: =C2-C3 | D4: =D2-D3
A5: Gross Margin % | B5: =B4/B2 | C5: =C4/C2 | D5: =D4/D2
A6: Monthly Churn Rate | B6: ='1. Assumptions'!B18 | C6: ='1. Assumptions'!C18 | D6: ='1. Assumptions'!D18
A7: Avg Customer Lifetime (thang) | B7: =1/B6 | C7: =1/C6 | D7: =1/D6
A8: LTV (Trieu VND/khach) | B8: =B4*B7 | C8: =C4*C7 | D8: =D4*D7
A9: CAC (Trieu VND/khach) | B9: ='1. Assumptions'!B21 | C9: ='1. Assumptions'!C21 | D9: ='1. Assumptions'!D21
A10: LTV / CAC Ratio | B10: =B8/B9 | C10: =C8/C9 | D10: =D8/D9
A11: CAC Payback (thang) | B11: =B9/B4 | C11: =C9/C4 | D11: =D9/D4
A12: Status | B12: =IF(AND(B10>3,B11<12,B5>=0.5),"HEALTHY","UNHEALTHY") | C12: =IF(AND(C10>3,C11<12,C5>=0.5),"HEALTHY","UNHEALTHY") | D12: =IF(AND(D10>3,D11<12,D5>=0.5),"HEALTHY","UNHEALTHY")

Sheet 3. P&L & ROI
A1: Scenario: | B1: Base
A3: Active Scenario Parameters:
A4: New Customers / thang | B4: =INDEX('1. Assumptions'!$B$5:$D$5,MATCH($B$1,'1. Assumptions'!$B$1:$D$1,0))*INDEX('1. Assumptions'!$B$4:$D$4,MATCH($B$1,'1. Assumptions'!$B$1:$D$1,0))
A5: ARPU (M/thang) | B5: =INDEX('1. Assumptions'!$B$3:$D$3,MATCH($B$1,'1. Assumptions'!$B$1:$D$1,0))
A6: COGS (M/khach/thang) | B6: =INDEX('1. Assumptions'!$B$15:$D$15,MATCH($B$1,'1. Assumptions'!$B$1:$D$1,0))
A7: Churn Rate | B7: =INDEX('1. Assumptions'!$B$18:$D$18,MATCH($B$1,'1. Assumptions'!$B$1:$D$1,0))
A8: CAC (M/khach) | B8: =INDEX('1. Assumptions'!$B$21:$D$21,MATCH($B$1,'1. Assumptions'!$B$1:$D$1,0))
A9: Fixed Cost (M/thang) | B9: =INDEX('1. Assumptions'!$B$27:$D$27,MATCH($B$1,'1. Assumptions'!$B$1:$D$1,0))
A10: Initial Investment (M) | B10: =INDEX('1. Assumptions'!$B$30:$D$30,MATCH($B$1,'1. Assumptions'!$B$1:$D$1,0))
A11: Initial Cash (M) | B11: =INDEX('1. Assumptions'!$B$31:$D$31,MATCH($B$1,'1. Assumptions'!$B$1:$D$1,0))
A12: Discount Rate (nam) | B12: =INDEX('1. Assumptions'!$B$32:$D$32,MATCH($B$1,'1. Assumptions'!$B$1:$D$1,0))
A13: Monthly Discount Rate | B13: =(1+B12)^(1/12)-1
A15: 36-MONTH PROJECTION
A16: Month | B16: Cust Start | C16: New | D16: Churned | E16: Cust End | F16: Revenue | G16: COGS | H16: Gross Profit | I16: S&M Cost | J16: Fixed Cost | K16: Net CF | L16: Cash Position
A17: 0 | B17: 0 | C17: 0 | D17: 0 | E17: 0 | F17: 0 | G17: 0 | H17: 0 | I17: 0 | J17: 0 | K17: =-B10 | L17: =B11+K17
A18: 1 | B18: =E17 | C18: =$B$4 | D18: =B18*$B$7 | E18: =B18-D18+C18 | F18: =E18*$B$5 | G18: =E18*$B$6 | H18: =F18-G18 | I18: =C18*$B$8 | J18: =$B$9 | K18: =H18-I18-J18 | L18: =L17+K18
A19: 2 | B19: =E18 | C19: =$B$4 | D19: =B19*$B$7 | E19: =B19-D19+C19 | F19: =E19*$B$5 | G19: =E19*$B$6 | H19: =F19-G19 | I19: =C19*$B$8 | J19: =$B$9 | K19: =H19-I19-J19 | L19: =L18+K19
A20: 3 | B20: =E19 | C20: =$B$4 | D20: =B20*$B$7 | E20: =B20-D20+C20 | F20: =E20*$B$5 | G20: =E20*$B$6 | H20: =F20-G20 | I20: =C20*$B$8 | J20: =$B$9 | K20: =H20-I20-J20 | L20: =L19+K20
A21: 4 | B21: =E20 | C21: =$B$4 | D21: =B21*$B$7 | E21: =B21-D21+C21 | F21: =E21*$B$5 | G21: =E21*$B$6 | H21: =F21-G21 | I21: =C21*$B$8 | J21: =$B$9 | K21: =H21-I21-J21 | L21: =L20+K21
A22: 5 | B22: =E21 | C22: =$B$4 | D22: =B22*$B$7 | E22: =B22-D22+C22 | F22: =E22*$B$5 | G22: =E22*$B$6 | H22: =F22-G22 | I22: =C22*$B$8 | J22: =$B$9 | K22: =H22-I22-J22 | L22: =L21+K22
A23: 6 | B23: =E22 | C23: =$B$4 | D23: =B23*$B$7 | E23: =B23-D23+C23 | F23: =E23*$B$5 | G23: =E23*$B$6 | H23: =F23-G23 | I23: =C23*$B$8 | J23: =$B$9 | K23: =H23-I23-J23 | L23: =L22+K23
A24: 7 | B24: =E23 | C24: =$B$4 | D24: =B24*$B$7 | E24: =B24-D24+C24 | F24: =E24*$B$5 | G24: =E24*$B$6 | H24: =F24-G24 | I24: =C24*$B$8 | J24: =$B$9 | K24: =H24-I24-J24 | L24: =L23+K24
A25: 8 | B25: =E24 | C25: =$B$4 | D25: =B25*$B$7 | E25: =B25-D25+C25 | F25: =E25*$B$5 | G25: =E25*$B$6 | H25: =F25-G25 | I25: =C25*$B$8 | J25: =$B$9 | K25: =H25-I25-J25 | L25: =L24+K25
A26: 9 | B26: =E25 | C26: =$B$4 | D26: =B26*$B$7 | E26: =B26-D26+C26 | F26: =E26*$B$5 | G26: =E26*$B$6 | H26: =F26-G26 | I26: =C26*$B$8 | J26: =$B$9 | K26: =H26-I26-J26 | L26: =L25+K26
A27: 10 | B27: =E26 | C27: =$B$4 | D27: =B27*$B$7 | E27: =B27-D27+C27 | F27: =E27*$B$5 | G27: =E27*$B$6 | H27: =F27-G27 | I27: =C27*$B$8 | J27: =$B$9 | K27: =H27-I27-J27 | L27: =L26+K27
A28: 11 | B28: =E27 | C28: =$B$4 | D28: =B28*$B$7 | E28: =B28-D28+C28 | F28: =E28*$B$5 | G28: =E28*$B$6 | H28: =F28-G28 | I28: =C28*$B$8 | J28: =$B$9 | K28: =H28-I28-J28 | L28: =L27+K28
A29: 12 | B29: =E28 | C29: =$B$4 | D29: =B29*$B$7 | E29: =B29-D29+C29 | F29: =E29*$B$5 | G29: =E29*$B$6 | H29: =F29-G29 | I29: =C29*$B$8 | J29: =$B$9 | K29: =H29-I29-J29 | L29: =L28+K29
... A53: 36 | B53: =E52 | C53: =$B$4 | D53: =B53*$B$7 | E53: =B53-D53+C53 | F53: =E53*$B$5 | G53: =E53*$B$6 | H53: =F53-G53 | I53: =C53*$B$8 | J53: =$B$9 | K53: =H53-I53-J53 | L53: =L52+K53
A56: KEY PERFORMANCE INDICATORS
A57: Break-even Month (Net CF > 0 dau tien) | B57: {=IFERROR(INDEX(A18:A53,MATCH(TRUE,K18:K53>0,0)),"N/A")}
A58: NPV 36 thang (Trieu VND) | B58: =IFERROR(K17+NPV(B13,K18:K53),0)
A59: IRR Monthly % | B59: =IFERROR(IRR(K17:K53)*100,0)
A60: IRR Annualized % | B60: =IFERROR(((1+B59/100)^12-1)*100,0)
A61: Project Payback (thang, Cash ve muc Initial Cash) | B61: {=IFERROR(INDEX(A17:A53,MATCH(TRUE,L17:L53>=B11,0)),"N/A")}
A62: Min Cash Position (Month 0-12) | B62: =MIN(L17:L29)
A63: Cash Position tai Month 12 | B63: =L29
A64: Runway (thang dau tien Cash < 0, hoac 36 neu khong am) | B64: {=IFERROR(INDEX(A17:A53,MATCH(TRUE,L17:L53<0,0)),36)}
